s3_log_extraction/__init__.py
s3_log_extraction/_hidden_top_level_imports.py
s3_log_extraction/_command_line_interface/__init__.py
s3_log_extraction/_command_line_interface/_cli.py
s3_log_extraction/_parallel/_utils.py
s3_log_extraction/_regex/__init__.py
s3_log_extraction/_regex/_globals.py
s3_log_extraction/config/__init__.py
s3_log_extraction/config/_config.py
s3_log_extraction/config/_globals.py
s3_log_extraction/config/_reset.py
s3_log_extraction/encryption_utils/__init__.py
s3_log_extraction/encryption_utils/_encryption.py
s3_log_extraction/extractors/__init__.py
s3_log_extraction/extractors/_generic_extraction.awk
s3_log_extraction/extractors/_globals.py
s3_log_extraction/extractors/_remote_s3_log_access_extractor.py
s3_log_extraction/extractors/_s3_log_access_extractor.py
s3_log_extraction/extractors/_stop.py
s3_log_extraction/extractors/_utils.py
s3_log_extraction/ip_utils/__init__.py
s3_log_extraction/ip_utils/_globals.py
s3_log_extraction/ip_utils/_index_ips.py
s3_log_extraction/ip_utils/_ip_cache.py
s3_log_extraction/ip_utils/_ip_utils.py
s3_log_extraction/ip_utils/_update_index_to_region_codes.py
s3_log_extraction/ip_utils/_update_region_code_coordinates.py
s3_log_extraction/summarize/__init__.py
s3_log_extraction/summarize/_generate_all_dataset_totals.py
s3_log_extraction/summarize/_generate_archive_summaries.py
s3_log_extraction/summarize/_generate_archive_totals.py
s3_log_extraction/summarize/_generate_summaries.py
s3_log_extraction/testing/__init__.py
s3_log_extraction/testing/_assertions.py
s3_log_extraction/testing/_benchmarking.py
s3_log_extraction/validate/__init__.py
s3_log_extraction/validate/_base_validator.py
s3_log_extraction/validate/_extraction_heuristic_pre_validator.py
s3_log_extraction/validate/_extraction_heuristic_pre_validator_script.awk
s3_log_extraction/validate/_http_empty_split_pre_validator.py
s3_log_extraction/validate/_http_empty_split_pre_validator_script.awk
s3_log_extraction/validate/_http_split_count_pre_validator.py
s3_log_extraction-1.3.1.dist-info/METADATA
s3_log_extraction-1.3.1.dist-info/WHEEL
s3_log_extraction-1.3.1.dist-info/entry_points.txt
s3_log_extraction-1.3.1.dist-info/licenses/LICENSE.txt
s3_log_extraction-1.3.1.dist-info/RECORD
