Metadata-Version: 2.4
Name: s3-log-extraction
Version: 1.3.1
Summary: Fast extraction of access summary data from S3 logs.
Project-URL: Documentation, https://github.com/dandi/s3-log-extraction/blob/master/README.md
Project-URL: Repository, https://github.com/dandi/s3-log-extraction/
Project-URL: Issues, https://github.com/dandi/s3-log-extraction/issues
Project-URL: Changelog, https://github.com/dandi/s3-log-extraction/blob/master/CHANGELOG.md
Author-email: Cody Baker <cody.c.baker.phd@gmail.com>
License: MIT License
License-File: LICENSE.txt
Keywords: AWS,S3,access stats,data infrastructure,download tracking,geolocation,logging,open data,usage analysis
Classifier: Development Status :: 5 - Production/Stable
Classifier: Intended Audience :: Developers
Classifier: License :: OSI Approved :: MIT License
Classifier: Operating System :: MacOS
Classifier: Operating System :: Unix
Classifier: Programming Language :: Python
Classifier: Programming Language :: Python :: 3.13
Classifier: Topic :: Scientific/Engineering :: Information Analysis
Requires-Python: >=3.13
Requires-Dist: cryptography
Requires-Dist: natsort
Requires-Dist: pandas
Requires-Dist: psutil
Requires-Dist: pydantic
Requires-Dist: pyyaml
Requires-Dist: rich-click
Requires-Dist: tqdm
Provides-Extra: all
Requires-Dist: fsspec; extra == 'all'
Requires-Dist: ipinfo; extra == 'all'
Requires-Dist: opencage; extra == 'all'
Requires-Dist: polars; extra == 'all'
Requires-Dist: s3fs; extra == 'all'
Requires-Dist: s5cmd; extra == 'all'
Provides-Extra: geolocation
Requires-Dist: ipinfo; extra == 'geolocation'
Requires-Dist: opencage; extra == 'geolocation'
Provides-Extra: remote
Requires-Dist: fsspec; extra == 'remote'
Requires-Dist: s3fs; extra == 'remote'
Requires-Dist: s5cmd; extra == 'remote'
Provides-Extra: sharing
Requires-Dist: polars; extra == 'sharing'
